[
	{
		"name": "id",
		"dbType": "increments",
		"htmlType": "",
		"validations": "",
		"primary": true,
		"searchable": false,
		"fillable": false,
		"inForm": false,
		"inIndex": false
	},
	{
		"name": "classroom_id",
		"dbType": "integer:unsigned:foreign,classrooms,id",
		"htmlType": "select,Classroom:id",
		"relation": "mt1,Classroom,classroom_id,id",
		"validations": "required",
		"primary": false,
		"searchable": true,
		"fillable": true,
		"inForm": true,
		"inIndex": true
	},
	{
		"name": "date",
		"dbType": "string",
		"htmlType": "text",
		"validations": "required",
		"primary": false,
		"searchable": true,
		"fillable": true,
		"inForm": true,
		"inIndex": true
	},
	{
		"name": "content",
		"dbType": "string",
		"htmlType": "textarea",
		"validations": "required",
		"primary": false,
		"searchable": true,
		"fillable": true,
		"inForm": true,
		"inIndex": true
	},
	{
		"name": "created_at",
		"dbType": "timestamp",
		"htmlType": "",
		"validations": "",
		"primary": false,
		"searchable": false,
		"fillable": false,
		"inForm": false,
		"inIndex": false
	},
	{
		"name": "updated_at",
		"dbType": "timestamp",
		"htmlType": "",
		"validations": "",
		"primary": false,
		"searchable": false,
		"fillable": false,
		"inForm": false,
		"inIndex": false
	}
]